mjcast/__init__.py
mjcast/modules/__init__.py
mjcast/modules/server.py
mjcast/plugins/__init__.py
mjcast/plugins/playlist.py
mjcast-0.1.12.data/scripts/mjcast
mjcast-0.1.12.dist-info/DESCRIPTION.rst
mjcast-0.1.12.dist-info/METADATA
mjcast-0.1.12.dist-info/RECORD
mjcast-0.1.12.dist-info/WHEEL
mjcast-0.1.12.dist-info/metadata.json
mjcast-0.1.12.dist-info/top_level.txt
