Metadata-Version: 2.0
Name: mjcast
Version: 0.1.12
Summary: Streaming MJPEG screenshots
Home-page: https://github.com/decryptus/mjcast
Author: doowan
Author-email: pypi@doowan.net
License: License GPL-2
Platform: UNKNOWN
Requires-Python: <3
Requires-Dist: dwho (>=0.2.89)
Requires-Dist: httpdis (>=0.5.13)
Requires-Dist: opencv-python
Requires-Dist: redis (>=2.4.0)
Requires-Dist: selenium
Requires-Dist: sonicprobe (>=0.2.69)
